kjmarotools/__init__.py
kjmarotools/_about.py
kjmarotools/proprietdin.py
kjmarotools/basics/__init__.py
kjmarotools/basics/conventions.py
kjmarotools/basics/convert.py
kjmarotools/basics/filetools.py
kjmarotools/basics/logtools.py
kjmarotools/basics/ostools.py
kjmarotools-0.1.1.dist-info/LICENSE
kjmarotools-0.1.1.dist-info/METADATA
kjmarotools-0.1.1.dist-info/WHEEL
kjmarotools-0.1.1.dist-info/top_level.txt
kjmarotools-0.1.1.dist-info/RECORD
